pynla/__init__.py
pynla-0.0.1.dist-info/METADATA
pynla-0.0.1.dist-info/WHEEL
pynla-0.0.1.dist-info/top_level.txt
pynla-0.0.1.dist-info/RECORD
