Metadata-Version: 2.4
Name: pynla
Version: 0.0.1
Summary: Modern, GPU-accelerated Numerical Linear Algebra for Python. (Coming Soon)
Author-email: Massimo Fedrigo <massimo@massimofedrigo.com>
License: MIT
Classifier: Development Status :: 1 - Planning
Classifier: Programming Language :: Python :: 3
Requires-Python: >=3.9
